{"cameraMode":{"drawMode":0,"name":"Shaded","section":"Shading Mode"},"sceneLighting":false,"audioPlay":false,"sceneViewState":{"m_AlwaysRefresh":false,"showFog":true,"showSkybox":false,"showFlares":true,"showImageEffects":true,"showParticleSystems":true,"showVisualEffectGraphs":true,"m_FxEnabled":true},"in2DMode":false,"pivot":{"x":135.97119140625,"y":5.812925815582275,"z":599.130126953125},"rotation":{"x":-0.019720731303095819,"y":-0.9770733714103699,"z":0.10445351898670197,"w":-0.18446983397006989},"size":10.765153884887696,"orthographic":false}